[
    {
        "id":17,
        "name": "Parotta & Gravy",
        "description": "Soft parotta served with spicy chicken gravy and chutney.",
        "price": 150,
        "image": "https://res.cloudinary.com/thanushan/image/upload/v1747015982/d-1-barotta_rzoh5h.webp"
    },
    {
        "id":18,
        "name": "Kottu Roti",
        "description": "Chopped roti with beef, eggs, vegetables, curry, and onions.",
        "price": 700,
        "image": "https://res.cloudinary.com/thanushan/image/upload/v1747015982/d-2-kottu_vaxt9o.webp"
    },
    {
        "id":19,
        "name": "Egg Roti & Sambol",
        "description": "Flatbread with egg, pol sambol, and spicy curry with sauce.",
        "price": 250,
        "image": "https://res.cloudinary.com/thanushan/image/upload/v1747015982/d-3-egg-roti_avtu5a.webp"
    },
    {
        "id":20,
        "name": "Egg Hoppers",
        "description": "Egg hoppers served with coconut milk gravy, sambol, and egg.",
        "price": 250,
        "image": "https://res.cloudinary.com/thanushan/image/upload/v1747015983/d-4-egg-hoppers_rfikuk.webp"
    },
    {
        "id":21,
        "name": "String Hoppers",
        "description": "Soft string hoppers served with spicy curry, sambol, and meat.",
        "price": 300,
        "image": "https://res.cloudinary.com/thanushan/image/upload/v1747015984/d-5-string-hoppers_bxexwc.webp"
    },
    {
        "id":22,
        "name": "Chicken Shawarma",
        "description": "Flatbread with chicken, garlic taste sauce, veggies, and spicy filling.",
        "price": 600,
        "image": "https://res.cloudinary.com/thanushan/image/upload/v1747016000/d-6-chicken-shawarama_hxm8yg.webp"
    },
    {
        "id":23,
        "name": "Noodles with Egg",
        "description": "Stir-fried noodles with vegetables, egg, spices, and soy sauce.",
        "price": 450,
        "image": "https://res.cloudinary.com/thanushan/image/upload/v1747015988/d-7-noodles-egg_kjodob.webp"
    },
    {
        "id":24,
        "name": "Chicken Roti Rolls",
        "description": "Spicy chicken wrapped in roti and grilled until crispy outside.",
        "price": 350,
        "image": "https://res.cloudinary.com/thanushan/image/upload/v1747015986/d-8-chicken-rotti_c7clx0.webp"
    }

]